space_x/__init__.py
space_x/space_x.py
space_x/utils/__init__.py
space_x/utils/section.py
space_x-0.3.2.dist-info/entry_points.txt
space_x-0.3.2.dist-info/WHEEL
space_x-0.3.2.dist-info/METADATA
space_x-0.3.2.dist-info/RECORD
