Metadata-Version: 2.1
Name: space-x
Version: 0.3.2
Summary: A hyperparameter optimizer for MoonLine.
Home-page: https://gitlab.genzai.dev/boosting-alpha/space-x
License: MIT
Author: Tim Wedde
Author-email: timwedde@icloud.com
Requires-Python: >=3.8,<4.0
Classifier: License :: OSI Approved :: MIT License
Classifier: Programming Language :: Python :: 3
Classifier: Programming Language :: Python :: 3.8
Classifier: Programming Language :: Python :: 3.9
Requires-Dist: arm-mango (>=1.1.0,<2.0.0)
Requires-Dist: click (>=8.0.1,<9.0.0)
Requires-Dist: numpy (>=1.20.3,<2.0.0)
Requires-Dist: rich (>=10.4.0,<11.0.0)
Project-URL: Repository, https://gitlab.genzai.dev/boosting-alpha/space-x
